bokeh_hj3415/__init__.py
bokeh_hj3415/data.py
bokeh_hj3415/graphs.py
bokeh_hj3415-0.2.0.dist-info/LICENSE
bokeh_hj3415-0.2.0.dist-info/METADATA
bokeh_hj3415-0.2.0.dist-info/WHEEL
bokeh_hj3415-0.2.0.dist-info/top_level.txt
bokeh_hj3415-0.2.0.dist-info/RECORD
