Metadata-Version: 2.1
Name: bokeh-hj3415
Version: 0.2.0
Summary: Make a graph.
Home-page: https://pypi.org/project/bokeh-hj3415/
Author: hyungjin kim
Author-email: hj3415@gmail.com
License: UNKNOWN
Project-URL: Bug Tracker, https://pypi.org/project/bokeh-hj3415/
Platform: UNKNOWN
Classifier: Programming Language :: Python :: 3
Classifier: License :: OSI Approved :: MIT License
Classifier: Operating System :: OS Independent
Requires-Python: >=3.6
License-File: LICENSE
Requires-Dist: bokeh (>=2.4.2)
Requires-Dist: db-hj3415 (>=1.2.1)
